mpi/__init__.py
mpi/block.py
mpi/connection.py
mpi/entity.py
mpi/event.py
mpi/fonts.py
mpi/minecraft.py
mpi/minecraftstuff.py
mpi/text.py
mpi/util.py
mpi/vec3.py
mpi-1.0.0.dist-info/LICENSE
mpi-1.0.0.dist-info/METADATA
mpi-1.0.0.dist-info/WHEEL
mpi-1.0.0.dist-info/top_level.txt
mpi-1.0.0.dist-info/RECORD
