Metadata-Version: 2.1
Name: mpi
Version: 1.0.0
Summary: Minecraft Pi API
Home-page: https://github.com/rdhuht/MinecraftPython/blob/master/README.md
Author: rdhuht
Author-email: xinhuaxilu6@gmail.com
License: UNKNOWN
Platform: UNKNOWN
Classifier: Programming Language :: Python :: 3
Classifier: License :: OSI Approved :: MIT License
Classifier: Operating System :: OS Independent
Requires-Python: >=3.6
